pyzshcomplete/__init__.py
pyzshcomplete/adapters/__init__.py
pyzshcomplete/adapters/argparse/__init__.py
pyzshcomplete/adapters/argparse/argument_adapter.py
pyzshcomplete/adapters/argparse/parser_adapter.py
pyzshcomplete/adapters/base/__init__.py
pyzshcomplete/adapters/base/argument_adapter.py
pyzshcomplete/adapters/base/parser_adapter.py
pyzshcomplete/tests/__init__.py
pyzshcomplete/tests/conftest.py
pyzshcomplete/tests/argparse/__init__.py
pyzshcomplete/tests/argparse/conftest.py
pyzshcomplete/tests/argparse/test_flag.py
pyzshcomplete/tests/argparse/test_full_examples.py
pyzshcomplete/tests/argparse/test_parser_features.py
pyzshcomplete/tests/argparse/test_positional.py
pyzshcomplete/tests/argparse/test_simple.py
pyzshcomplete/utils/__init__.py
pyzshcomplete/utils/zsh_constants.py
pyzshcomplete/zsh_scripts/_python_or_script
pyzshcomplete/zsh_scripts/_python_script
pyzshcomplete-1.0.3.data/scripts/activate_pyzshcomplete
pyzshcomplete-1.0.3.dist-info/LICENSE
pyzshcomplete-1.0.3.dist-info/METADATA
pyzshcomplete-1.0.3.dist-info/WHEEL
pyzshcomplete-1.0.3.dist-info/top_level.txt
pyzshcomplete-1.0.3.dist-info/RECORD
